{
  "plugins": {
    "nvim-lspconfig": {
      "rev": "2010fc6",
      "src": "https://github.com/neovim/nvim-lspconfig"
    },
    "nvim-treesitter": {
      "rev": "81aec1e4",
      "src": "https://github.com/nvim-treesitter/nvim-treesitter",
      "version": "'main'"
    },
    "tree-sitter-test": {
      "rev": "76b419f",
      "src": "https://github.com/tree-sitter-grammars/tree-sitter-test"
    },
    "vague.nvim": {
      "rev": "27a154c",
      "src": "https://github.com/skewb1k/vague.nvim"
    },
    "vie.nvim": {
      "rev": "daa286b",
      "src": "https://github.com/vietmpl/vie.nvim"
    }
  }
}